[
{"type":"header","version":"5.2.0","comment":"Export to JSON plugin for PHPMyAdmin"},
{"type":"database","name":"data_penduduk"},
{"type":"table","name":"datadetail","database":"data_penduduk","data":
[
{"id_detail":"1","Kabupaten\/Kota":"Buton","Jumlah Penduduk":"118410","Angka Harapan Hidup":"68.46","Jumlah yang Masih Sekolah":"79.14","Tingkat Partisipasi Angkatan Kerja (TPAK)":"77.34","Pengeluaran per Kapita Disesuaikan (Ribu Rupiah)":"7594","Akses Air Minum Layak":"98.53","Jumlah Penduduk Miskin":"13.61","Indeks Pembangunan Manusia":"67.23","Tingkat Pengangguran Terbuka (TPT)":"2.99","Sejahtera \/ Tidak Sejahtera":"1","Jumlah Penduduk Laki-Laki":"72230","Jumlah Penduduk Perempuan":"60389"},
{"id_detail":"2","Kabupaten\/Kota":"Muna","Jumlah Penduduk":"221370","Angka Harapan Hidup":"70.47","Jumlah yang Masih Sekolah":"79.73","Tingkat Partisipasi Angkatan Kerja (TPAK)":"66.41","Pengeluaran per Kapita Disesuaikan (Ribu Rupiah)":"8328","Akses Air Minum Layak":"96.1","Jumlah Penduduk Miskin":"30.48","Indeks Pembangunan Manusia":"69.61","Tingkat Pengangguran Terbuka (TPT)":"3.11","Sejahtera \/ Tidak Sejahtera":"1","Jumlah Penduduk Laki-Laki":"135036","Jumlah Penduduk Perempuan":"112899"},
{"id_detail":"3","Kabupaten\/Kota":"Konawe","Jumlah Penduduk":"264930","Angka Harapan Hidup":"70.38","Jumlah yang Masih Sekolah":"69.94","Tingkat Partisipasi Angkatan Kerja (TPAK)":"66.81","Pengeluaran per Kapita Disesuaikan (Ribu Rupiah)":"10552","Akses Air Minum Layak":"86.26","Jumlah Penduduk Miskin":"32.09","Indeks Pembangunan Manusia":"72.04","Tingkat Pengangguran Terbuka (TPT)":"2.73","Sejahtera \/ Tidak Sejahtera":"1","Jumlah Penduduk Laki-Laki":"161607","Jumlah Penduduk Perempuan":"135114"},
{"id_detail":"4","Kabupaten\/Kota":"Kolaka","Jumlah Penduduk":"243040","Angka Harapan Hidup":"71.3","Jumlah yang Masih Sekolah":"68.2","Tingkat Partisipasi Angkatan Kerja (TPAK)":"64.49","Pengeluaran per Kapita Disesuaikan (Ribu Rupiah)":"12639","Akses Air Minum Layak":"97.68","Jumlah Penduduk Miskin":"31.56","Indeks Pembangunan Manusia":"73.98","Tingkat Pengangguran Terbuka (TPT)":"4.17","Sejahtera \/ Tidak Sejahtera":"1","Jumlah Penduduk Laki-Laki":"148254","Jumlah Penduduk Perempuan":"123950"},
{"id_detail":"5","Kabupaten\/Kota":"Konawe Selatan","Jumlah Penduduk":"318350","Angka Harapan Hidup":"70.95","Jumlah yang Masih Sekolah":"68.82","Tingkat Partisipasi Angkatan Kerja (TPAK)":"69.46","Pengeluaran per Kapita Disesuaikan (Ribu Rupiah)":"9347","Akses Air Minum Layak":"89.75","Jumlah Penduduk Miskin":"35.79","Indeks Pembangunan Manusia":"69.36","Tingkat Pengangguran Terbuka (TPT)":"2.95","Sejahtera \/ Tidak Sejahtera":"1","Jumlah Penduduk Laki-Laki":"194194","Jumlah Penduduk Perempuan":"162358"},
{"id_detail":"6","Kabupaten\/Kota":"Bombana","Jumlah Penduduk":"155510","Angka Harapan Hidup":"69.2","Jumlah yang Masih Sekolah":"66.27","Tingkat Partisipasi Angkatan Kerja (TPAK)":"68.3","Pengeluaran per Kapita Disesuaikan (Ribu Rupiah)":"8680","Akses Air Minum Layak":"98.72","Jumlah Penduduk Miskin":"19.21","Indeks Pembangunan Manusia":"66.81","Tingkat Pengangguran Terbuka (TPT)":"1.47","Sejahtera \/ Tidak Sejahtera":"1","Jumlah Penduduk Laki-Laki":"94861","Jumlah Penduduk Perempuan":"79310"},
{"id_detail":"7","Kabupaten\/Kota":"Wakatobi","Jumlah Penduduk":"114620","Angka Harapan Hidup":"70.59","Jumlah yang Masih Sekolah":"71.7","Tingkat Partisipasi Angkatan Kerja (TPAK)":"73.39","Pengeluaran per Kapita Disesuaikan (Ribu Rupiah)":"9758","Akses Air Minum Layak":"97.38","Jumlah Penduduk Miskin":"15.01","Indeks Pembangunan Manusia":"70.85","Tingkat Pengangguran Terbuka (TPT)":"3.53","Sejahtera \/ Tidak Sejahtera":"1","Jumlah Penduduk Laki-Laki":"69918","Jumlah Penduduk Perempuan":"58456"},
{"id_detail":"8","Kabupaten\/Kota":"Kolaka Utara","Jumlah Penduduk":"142770","Angka Harapan Hidup":"70.4","Jumlah yang Masih Sekolah":"67.01","Tingkat Partisipasi Angkatan Kerja (TPAK)":"77.18","Pengeluaran per Kapita Disesuaikan (Ribu Rupiah)":"10721","Akses Air Minum Layak":"92.27","Jumlah Penduduk Miskin":"20.63","Indeks Pembangunan Manusia":"70.39","Tingkat Pengangguran Terbuka (TPT)":"2.86","Sejahtera \/ Tidak Sejahtera":"1","Jumlah Penduduk Laki-Laki":"87090","Jumlah Penduduk Perempuan":"72813"},
{"id_detail":"9","Kabupaten\/Kota":"Buton Utara","Jumlah Penduduk":"68090","Angka Harapan Hidup":"70.96","Jumlah yang Masih Sekolah":"74.36","Tingkat Partisipasi Angkatan Kerja (TPAK)":"81.23","Pengeluaran per Kapita Disesuaikan (Ribu Rupiah)":"7935","Akses Air Minum Layak":"95.72","Jumlah Penduduk Miskin":"9.13","Indeks Pembangunan Manusia":"69","Tingkat Pengangguran Terbuka (TPT)":"2.1","Sejahtera \/ Tidak Sejahtera":"1","Jumlah Penduduk Laki-Laki":"41535","Jumlah Penduduk Perempuan":"34726"},
{"id_detail":"10","Kabupaten\/Kota":"Konawe Utara","Jumlah Penduduk":"70680","Angka Harapan Hidup":"69.59","Jumlah yang Masih Sekolah":"69.17","Tingkat Partisipasi Angkatan Kerja (TPAK)":"71.64","Pengeluaran per Kapita Disesuaikan (Ribu Rupiah)":"9666","Akses Air Minum Layak":"89.02","Jumlah Penduduk Miskin":"9.02","Indeks Pembangunan Manusia":"71.1","Tingkat Pengangguran Terbuka (TPT)":"2.01","Sejahtera \/ Tidak Sejahtera":"1","Jumlah Penduduk Laki-Laki":"43115","Jumlah Penduduk Perempuan":"36047"},
{"id_detail":"11","Kabupaten\/Kota":"Kolaka Timur","Jumlah Penduduk":"123980","Angka Harapan Hidup":"72.9","Jumlah yang Masih Sekolah":"71.07","Tingkat Partisipasi Angkatan Kerja (TPAK)":"69.51","Pengeluaran per Kapita Disesuaikan (Ribu Rupiah)":"8155","Akses Air Minum Layak":"97.61","Jumlah Penduduk Miskin":"19.33","Indeks Pembangunan Manusia":"68.73","Tingkat Pengangguran Terbuka (TPT)":"2.22","Sejahtera \/ Tidak Sejahtera":"1","Jumlah Penduduk Laki-Laki":"75628","Jumlah Penduduk Perempuan":"63230"},
{"id_detail":"12","Kabupaten\/Kota":"Konawe Kepulauan","Jumlah Penduduk":"38310","Angka Harapan Hidup":"68.46","Jumlah yang Masih Sekolah":"73.41","Tingkat Partisipasi Angkatan Kerja (TPAK)":"68.65","Pengeluaran per Kapita Disesuaikan (Ribu Rupiah)":"7192","Akses Air Minum Layak":"89.01","Jumlah Penduduk Miskin":"5.47","Indeks Pembangunan Manusia":"66.69","Tingkat Pengangguran Terbuka (TPT)":"1.85","Sejahtera \/ Tidak Sejahtera":"1","Jumlah Penduduk Laki-Laki":"23369","Jumlah Penduduk Perempuan":"19538"},
{"id_detail":"13","Kabupaten\/Kota":"Muna Barat","Jumlah Penduduk":"87590","Angka Harapan Hidup":"70.39","Jumlah yang Masih Sekolah":"72.79","Tingkat Partisipasi Angkatan Kerja (TPAK)":"82.12","Pengeluaran per Kapita Disesuaikan (Ribu Rupiah)":"7668","Akses Air Minum Layak":"96.05","Jumlah Penduduk Miskin":"11.56","Indeks Pembangunan Manusia":"66.21","Tingkat Pengangguran Terbuka (TPT)":"2.4","Sejahtera \/ Tidak Sejahtera":"1","Jumlah Penduduk Laki-Laki":"53430","Jumlah Penduduk Perempuan":"44671"},
{"id_detail":"14","Kabupaten\/Kota":"Buton Tengah","Jumlah Penduduk":"117630","Angka Harapan Hidup":"67.78","Jumlah yang Masih Sekolah":"78.57","Tingkat Partisipasi Angkatan Kerja (TPAK)":"68.07","Pengeluaran per Kapita Disesuaikan (Ribu Rupiah)":"7670","Akses Air Minum Layak":"96.07","Jumlah Penduduk Miskin":"13.92","Indeks Pembangunan Manusia":"65.29","Tingkat Pengangguran Terbuka (TPT)":"2.63","Sejahtera \/ Tidak Sejahtera":"1","Jumlah Penduduk Laki-Laki":"71754","Jumlah Penduduk Perempuan":"59991"},
{"id_detail":"15","Kabupaten\/Kota":"Buton Selatan","Jumlah Penduduk":"97950","Angka Harapan Hidup":"67.76","Jumlah yang Masih Sekolah":"75.11","Tingkat Partisipasi Angkatan Kerja (TPAK)":"71.88","Pengeluaran per Kapita Disesuaikan (Ribu Rupiah)":"7476","Akses Air Minum Layak":"98.41","Jumlah Penduduk Miskin":"11.57","Indeks Pembangunan Manusia":"65.44","Tingkat Pengangguran Terbuka (TPT)":"4.18","Sejahtera \/ Tidak Sejahtera":"1","Jumlah Penduduk Laki-Laki":"59750","Jumlah Penduduk Perempuan":"49954"},
{"id_detail":"16","Kabupaten\/Kota":"Kendari","Jumlah Penduduk":"357650","Angka Harapan Hidup":"73.93","Jumlah yang Masih Sekolah":"83.78","Tingkat Partisipasi Angkatan Kerja (TPAK)":"65.48","Pengeluaran per Kapita Disesuaikan (Ribu Rupiah)":"14765","Akses Air Minum Layak":"95.27","Jumlah Penduduk Miskin":"18.72","Indeks Pembangunan Manusia":"84.51","Tingkat Pengangguran Terbuka (TPT)":"5.23","Sejahtera \/ Tidak Sejahtera":"1","Jumlah Penduduk Laki-Laki":"218166","Jumlah Penduduk Perempuan":"182402"},
{"id_detail":"17","Kabupaten\/Kota":"BauBau","Jumlah Penduduk":"163720","Angka Harapan Hidup":"71.36","Jumlah yang Masih Sekolah":"77.2","Tingkat Partisipasi Angkatan Kerja (TPAK)":"61.14","Pengeluaran per Kapita Disesuaikan (Ribu Rupiah)":"10835","Akses Air Minum Layak":"100","Jumlah Penduduk Miskin":"12.69","Indeks Pembangunan Manusia":"76.67","Tingkat Pengangguran Terbuka (TPT)":"5.39","Sejahtera \/ Tidak Sejahtera":"1","Jumlah Penduduk Laki-Laki":"99869","Jumlah Penduduk Perempuan":"83497"}
]
}
]
